README.md
setup.py
DoxyUML/__init__.py
DoxyUML/__main__.py
DoxyUML/classObj.py
DoxyUML/classParser.py
DoxyUML/commonParser.py
DoxyUML/dotExport.py
DoxyUML/doxyuml.py
DoxyUML/indexParser.py
DoxyUML/namespaceObj.py
DoxyUML/namespaceParser.py
DoxyUML.egg-info/PKG-INFO
DoxyUML.egg-info/SOURCES.txt
DoxyUML.egg-info/dependency_links.txt
DoxyUML.egg-info/requires.txt
DoxyUML.egg-info/top_level.txt